absplots.py
absplots-0.2.0.dist-info/COPYING
absplots-0.2.0.dist-info/METADATA
absplots-0.2.0.dist-info/WHEEL
absplots-0.2.0.dist-info/top_level.txt
absplots-0.2.0.dist-info/RECORD
