Metadata-Version: 2.1
Name: absplots
Version: 0.2.0
Summary: Matplotlib subplots with absolute margins in mm or inches
Home-page: http://github.com/juseg/absplots
Author: Julien Seguinot
Author-email: seguinot@vaw.baug.ethz.ch
License: gpl-3.0
Platform: UNKNOWN
Requires-Dist: matplotlib
